Workbook

Sheet Instructions
B2: Grant Tracking Spreadsheet
B3: A compliance-aware template for nonprofits — by GrantPipe
B5: WHAT'S INSIDE
B6: • Grant Register — one row per grant, with the restricted-funds and period-of-performance columns most trackers skip.
B7: • Budget vs Actual — track spend against each grant's budget, category by category. 'Spent' fills itself from the Expense Log.
B8: • Expense Log — one row per dollar charged to a grant. The Grant ID ties each expense back to its budget line.
B9: • Reporting — funder report deadlines, with colour warnings as due dates approach.
B11: HOW TO USE IT
B12: 1. List every grant on the Grant Register. Give each a short Grant ID (e.g. ED-2026-01) and mark whether it's Restricted.
B13: 2. On Budget vs Actual, enter the funder-approved budget by category for each Grant ID.
B14: 3. Log every expense on the Expense Log as it happens. 'Spent' and 'Remaining' update automatically.
B15: 4. Add funder report deadlines on Reporting. Rows turn amber within 30 days and red once overdue.
... B21: Free to use and share. Replace the sample rows with your own data.

Sheet Grant Register
A1: Total Awarded | C1: Total Spent | E1: % Restricted | G1: Reports Due / 30d
A2: =SUM(E4:E200) | C2: =SUM('Budget vs Actual'!D4:D400) | E2: =IF(SUM(E4:E200)=0,0,SUMIF(H4:H200,"Yes",E4:E200)/SUM(E4:E200)) | G2: =COUNTIFS(Reporting!C4:C200,"<="&(TODAY()+30),Reporting!C4:C200,">="&TODAY(),Reporting!D4:D200,"")
A3: Grant ID | B3: Grant Name | C3: Funder | D3: Funder Type | E3: Award Amount | F3: Start Date | G3: End Date | H3: Restricted? | I3: Restriction Purpose | J3: Status
A4: ED-2026-01 | B4: After-School STEM | C4: Dept. of Education | D4: Federal | E4: 50000 | F4: 45931 | G4: 46295 | H4: Yes | I4: STEM program only | J4: Active
A5: HF-2026-02 | B5: Family Literacy | C5: Hartwell Foundation | D5: Foundation | E5: 28000 | F5: 46023 | G5: 46387 | H5: Yes | I5: Literacy materials & staff | J5: Active
A6: ST-2026-03 | B6: Summer Meals | C6: State DHS | D6: State | E6: 41500 | F6: 46143 | G6: 46265 | H6: Yes | I6: Meal program only | J6: Awarded
A7: GEN-OPS-00 | B7: General Operating | C7: Community Fund | D7: Foundation | E7: 15000 | F7: 46023 | G7: 46387 | H7: No | I7: — | J7: Active

Sheet Budget vs Actual
A1: Grant ID | B1: Budget Category | C1: Budgeted | D1: Spent (auto) | E1: Remaining | F1: % Spent
A2: ED-2026-01 | B2: Personnel | C2: 32000 | D2: =SUMIFS('Expense Log'!$E$4:$E$1000,'Expense Log'!$B$4:$B$1000,A2,'Expense Log'!$C$4:$C$1000,B2) | E2: =C2-D2 | F2: =IF(C2=0,0,D2/C2)
A3: ED-2026-01 | B3: Supplies | C3: 6000 | D3: =SUMIFS('Expense Log'!$E$4:$E$1000,'Expense Log'!$B$4:$B$1000,A3,'Expense Log'!$C$4:$C$1000,B3) | E3: =C3-D3 | F3: =IF(C3=0,0,D3/C3)
A4: ED-2026-01 | B4: Travel | C4: 8000 | D4: =SUMIFS('Expense Log'!$E$4:$E$1000,'Expense Log'!$B$4:$B$1000,A4,'Expense Log'!$C$4:$C$1000,B4) | E4: =C4-D4 | F4: =IF(C4=0,0,D4/C4)
A5: ED-2026-01 | B5: Indirect (10%) | C5: 4000 | D5: =SUMIFS('Expense Log'!$E$4:$E$1000,'Expense Log'!$B$4:$B$1000,A5,'Expense Log'!$C$4:$C$1000,B5) | E5: =C5-D5 | F5: =IF(C5=0,0,D5/C5)
A6: HF-2026-02 | B6: Personnel | C6: 18000 | D6: =SUMIFS('Expense Log'!$E$4:$E$1000,'Expense Log'!$B$4:$B$1000,A6,'Expense Log'!$C$4:$C$1000,B6) | E6: =C6-D6 | F6: =IF(C6=0,0,D6/C6)
A7: HF-2026-02 | B7: Materials | C7: 10000 | D7: =SUMIFS('Expense Log'!$E$4:$E$1000,'Expense Log'!$B$4:$B$1000,A7,'Expense Log'!$C$4:$C$1000,B7) | E7: =C7-D7 | F7: =IF(C7=0,0,D7/C7)

Sheet Expense Log
A1: Log every dollar charged to a grant. 'Grant ID' + 'Category' must match the Budget vs Actual rows so SUMIFS can find them.
A3: Date | B3: Grant ID | C3: Category | D3: Vendor | E3: Amount | F3: Notes
A4: 46085 | B4: ED-2026-01 | C4: Supplies | D4: Lakeshore Learning | E4: 1240 | F4: Lab kits
A5: 46090 | B5: ED-2026-01 | C5: Travel | D5: Delta Air Lines | E5: 612 | F5: Site visit
A6: 46093 | B6: HF-2026-02 | C6: Personnel | D6: Payroll | E6: 3800 | F6: Tutor wages
A7: 46099 | B7: ED-2026-01 | C7: Personnel | D7: Payroll | E7: 4100 | F7: Instructor
A8: 46103 | B8: ED-2026-01 | C8: Travel | D8: Marriott | E8: 980 | F8: Conference

Sheet Reporting
A1: Due dates turn amber within 30 days and red once overdue and unsubmitted.
A3: Grant ID | B3: Report Type | C3: Due Date | D3: Submitted Date | E3: Status (auto)
A4: ED-2026-01 | B4: Quarterly Financial | C4: 46188 | E4: =IF(D4<>"","Submitted",IF(C4<TODAY(),"OVERDUE",IF(C4<=TODAY()+30,"Due soon","Upcoming")))
A5: HF-2026-02 | B5: Interim Narrative | C5: 46143 | E5: =IF(D5<>"","Submitted",IF(C5<TODAY(),"OVERDUE",IF(C5<=TODAY()+30,"Due soon","Upcoming")))
A6: ST-2026-03 | B6: Final Report | C6: 46295 | E6: =IF(D6<>"","Submitted",IF(C6<TODAY(),"OVERDUE",IF(C6<=TODAY()+30,"Due soon","Upcoming")))
